{
  "generated_at": "2026-03-23T15:14:12.948690",
  "total_count": 626,
  "by_drp": {
    "DRP-0159": [
      "DRP-0159_p4_1.jpeg"
    ],
    "DRP-0160": [
      "DRP-0160_p3_1.jpeg",
      "DRP-0160_p3_2.jpeg",
      "DRP-0160_p3_3.jpeg",
      "DRP-0160_p3_4.jpeg",
      "DRP-0160_p3_5.jpeg",
      "DRP-0160_p3_6.jpeg",
      "DRP-0160_p3_7.jpeg",
      "DRP-0160_p3_8.jpeg",
      "DRP-0160_p3_9.jpeg"
    ],
    "DRP-0161": [
      "DRP-0161_p4_1.jpeg",
      "DRP-0161_p4_2.jpeg"
    ],
    "DRP-0162": [
      "DRP-0162_p4_1.jpeg"
    ],
    "DRP-0164": [
      "DRP-0164_p4_1.jpeg"
    ],
    "DRP-0165": [
      "DRP-0165_p4_1.jpeg"
    ],
    "DRP-0166": [
      "DRP-0166_p4_1.jpeg"
    ],
    "DRP-0167": [
      "DRP-0167_p4_1.jpeg"
    ],
    "DRP-0168": [
      "DRP-0168_p4_1.jpeg"
    ],
    "DRP-0169": [
      "DRP-0169_p4_1.jpeg"
    ],
    "DRP-0170": [
      "DRP-0170_p4_1.jpeg"
    ],
    "DRP-0171": [
      "DRP-0171_p4_1.jpeg"
    ],
    "DRP-0173": [
      "DRP-0173_p4_1.jpeg"
    ],
    "DRP-0174": [
      "DRP-0174_p4_1.jpeg"
    ],
    "DRP-0175": [
      "DRP-0175_p4_1.jpeg"
    ],
    "DRP-0176": [
      "DRP-0176_p4_1.jpeg"
    ],
    "DRP-0177": [
      "DRP-0177_p4_1.jpeg"
    ],
    "DRP-0178": [
      "DRP-0178_p4_1.jpeg"
    ],
    "DRP-0179": [
      "DRP-0179_p4_1.jpeg"
    ],
    "DRP-0180": [
      "DRP-0180_p4_1.jpeg"
    ],
    "DRP-0181": [
      "DRP-0181_p4_1.jpeg"
    ],
    "DRP-0182": [
      "DRP-0182_p4_1.jpeg"
    ],
    "DRP-0183": [
      "DRP-0183_p4_1.jpeg"
    ],
    "DRP-0184": [
      "DRP-0184_p4_1.jpeg"
    ],
    "DRP-0188": [
      "DRP-0188_p3_1.jpeg"
    ],
    "DRP-0189": [
      "DRP-0189_p3_1.jpeg"
    ],
    "DRP-0190": [
      "DRP-0190_p4_1.jpeg"
    ],
    "DRP-0191": [
      "DRP-0191_p4_1.jpeg"
    ],
    "DRP-0192": [
      "DRP-0192_p4_1.jpeg"
    ],
    "DRP-0193": [
      "DRP-0193_p4_1.jpeg"
    ],
    "DRP-0194": [
      "DRP-0194_p4_1.jpeg"
    ],
    "DRP-0195": [
      "DRP-0195_p4_1.jpeg"
    ],
    "DRP-0196": [
      "DRP-0196_p4_1.jpeg"
    ],
    "DRP-0198": [
      "DRP-0198_p4_1.jpeg"
    ],
    "DRP-0200": [
      "DRP-0200_p4_1.jpeg"
    ],
    "DRP-0201": [
      "DRP-0201_p4_1.jpeg"
    ],
    "DRP-0202": [
      "DRP-0202_p4_1.jpeg"
    ],
    "DRP-0203": [
      "DRP-0203_p4_1.jpeg"
    ],
    "DRP-0204": [
      "DRP-0204_p4_1.jpeg"
    ],
    "DRP-0205": [
      "DRP-0205_p4_1.jpeg"
    ],
    "DRP-0206": [
      "DRP-0206_p4_1.jpeg"
    ],
    "DRP-0207": [
      "DRP-0207_p4_1.jpeg"
    ],
    "DRP-0208": [
      "DRP-0208_p4_1.jpeg"
    ],
    "DRP-0209": [
      "DRP-0209_p4_1.jpeg"
    ],
    "DRP-0210": [
      "DRP-0210_p4_1.jpeg"
    ],
    "DRP-0211": [
      "DRP-0211_p4_1.jpeg"
    ],
    "DRP-0212": [
      "DRP-0212_p4_1.jpeg"
    ],
    "DRP-0213": [
      "DRP-0213_p4_1.jpeg"
    ],
    "DRP-0214": [
      "DRP-0214_p4_1.jpeg"
    ],
    "DRP-0215": [
      "DRP-0215_p4_1.jpeg"
    ],
    "DRP-0216": [
      "DRP-0216_p4_1.jpeg"
    ],
    "DRP-0217": [
      "DRP-0217_p4_1.jpeg"
    ],
    "DRP-0218": [
      "DRP-0218_p4_1.jpeg"
    ],
    "DRP-0219": [
      "DRP-0219_p4_1.jpeg"
    ],
    "DRP-0221": [
      "DRP-0221_p4_1.jpeg"
    ],
    "DRP-0223": [
      "DRP-0223_p4_1.jpeg"
    ],
    "DRP-0225": [
      "DRP-0225_p4_1.jpeg"
    ],
    "DRP-0227": [
      "DRP-0227_p4_1.jpeg"
    ],
    "DRP-0228": [
      "DRP-0228_p4_1.jpeg"
    ],
    "DRP-0230": [
      "DRP-0230_p4_1.jpeg"
    ],
    "DRP-0231": [
      "DRP-0231_p4_1.jpeg"
    ],
    "DRP-0232": [
      "DRP-0232_p4_1.jpeg"
    ],
    "DRP-0233": [
      "DRP-0233_p4_1.jpeg"
    ],
    "DRP-0234": [
      "DRP-0234_p4_1.jpeg"
    ],
    "DRP-0235": [
      "DRP-0235_p4_1.jpeg"
    ],
    "DRP-0236": [
      "DRP-0236_p4_1.jpeg"
    ],
    "DRP-0237": [
      "DRP-0237_p3_1.jpeg",
      "DRP-0237_p3_2.jpeg",
      "DRP-0237_p3_3.jpeg",
      "DRP-0237_p3_4.jpeg",
      "DRP-0237_p3_5.jpeg",
      "DRP-0237_p3_6.jpeg",
      "DRP-0237_p3_7.jpeg",
      "DRP-0237_p3_8.jpeg",
      "DRP-0237_p3_9.jpeg",
      "DRP-0237_p4_1.jpeg",
      "DRP-0237_p4_2.jpeg",
      "DRP-0237_p4_3.jpeg",
      "DRP-0237_p4_4.jpeg",
      "DRP-0237_p4_5.jpeg",
      "DRP-0237_p4_6.jpeg",
      "DRP-0237_p4_7.jpeg",
      "DRP-0237_p4_8.jpeg",
      "DRP-0237_p4_9.jpeg"
    ],
    "DRP-0238": [
      "DRP-0238_p3_1.jpeg",
      "DRP-0238_p3_2.jpeg",
      "DRP-0238_p3_3.jpeg",
      "DRP-0238_p3_4.jpeg",
      "DRP-0238_p3_5.jpeg",
      "DRP-0238_p3_6.jpeg",
      "DRP-0238_p4_1.jpeg",
      "DRP-0238_p4_2.jpeg",
      "DRP-0238_p4_3.jpeg",
      "DRP-0238_p4_4.jpeg",
      "DRP-0238_p4_5.jpeg",
      "DRP-0238_p4_6.jpeg"
    ],
    "DRP-0240": [
      "DRP-0240_p3_1.jpeg",
      "DRP-0240_p3_2.jpeg",
      "DRP-0240_p3_3.jpeg",
      "DRP-0240_p3_4.jpeg",
      "DRP-0240_p3_5.jpeg",
      "DRP-0240_p3_6.jpeg",
      "DRP-0240_p3_7.jpeg",
      "DRP-0240_p3_8.jpeg",
      "DRP-0240_p3_9.jpeg",
      "DRP-0240_p4_1.jpeg",
      "DRP-0240_p4_2.jpeg",
      "DRP-0240_p4_3.jpeg",
      "DRP-0240_p4_4.jpeg",
      "DRP-0240_p4_5.jpeg",
      "DRP-0240_p4_6.jpeg",
      "DRP-0240_p4_7.jpeg",
      "DRP-0240_p4_8.jpeg",
      "DRP-0240_p4_9.jpeg"
    ],
    "DRP-0241": [
      "DRP-0241_p3_1.jpeg",
      "DRP-0241_p3_2.jpeg",
      "DRP-0241_p3_3.jpeg",
      "DRP-0241_p3_4.jpeg",
      "DRP-0241_p3_5.jpeg",
      "DRP-0241_p3_6.jpeg",
      "DRP-0241_p3_7.jpeg",
      "DRP-0241_p3_8.jpeg",
      "DRP-0241_p3_9.jpeg",
      "DRP-0241_p4_1.jpeg",
      "DRP-0241_p4_2.jpeg",
      "DRP-0241_p4_3.jpeg",
      "DRP-0241_p4_4.jpeg",
      "DRP-0241_p4_5.jpeg",
      "DRP-0241_p4_6.jpeg",
      "DRP-0241_p4_7.jpeg",
      "DRP-0241_p4_8.jpeg",
      "DRP-0241_p4_9.jpeg"
    ],
    "DRP-0242": [
      "DRP-0242_p3_1.jpeg",
      "DRP-0242_p3_2.jpeg",
      "DRP-0242_p3_3.jpeg",
      "DRP-0242_p3_4.jpeg",
      "DRP-0242_p3_5.jpeg",
      "DRP-0242_p3_6.jpeg",
      "DRP-0242_p3_7.jpeg",
      "DRP-0242_p3_8.jpeg",
      "DRP-0242_p3_9.jpeg",
      "DRP-0242_p4_1.jpeg",
      "DRP-0242_p4_2.jpeg",
      "DRP-0242_p4_3.jpeg",
      "DRP-0242_p4_4.jpeg",
      "DRP-0242_p4_5.jpeg",
      "DRP-0242_p4_6.jpeg",
      "DRP-0242_p4_7.jpeg",
      "DRP-0242_p4_8.jpeg",
      "DRP-0242_p4_9.jpeg"
    ],
    "DRP-0243": [
      "DRP-0243_p3_1.jpeg",
      "DRP-0243_p3_2.jpeg",
      "DRP-0243_p3_3.jpeg",
      "DRP-0243_p3_4.jpeg",
      "DRP-0243_p3_5.jpeg",
      "DRP-0243_p3_6.jpeg",
      "DRP-0243_p3_7.jpeg",
      "DRP-0243_p3_8.jpeg",
      "DRP-0243_p3_9.jpeg",
      "DRP-0243_p4_1.jpeg",
      "DRP-0243_p4_2.jpeg",
      "DRP-0243_p4_3.jpeg",
      "DRP-0243_p4_4.jpeg",
      "DRP-0243_p4_5.jpeg",
      "DRP-0243_p4_6.jpeg",
      "DRP-0243_p4_7.jpeg",
      "DRP-0243_p4_8.jpeg",
      "DRP-0243_p4_9.jpeg"
    ],
    "DRP-0244": [
      "DRP-0244_p3_1.jpeg",
      "DRP-0244_p3_2.jpeg",
      "DRP-0244_p3_3.jpeg",
      "DRP-0244_p3_4.jpeg",
      "DRP-0244_p3_5.jpeg",
      "DRP-0244_p3_6.jpeg",
      "DRP-0244_p3_7.jpeg",
      "DRP-0244_p3_8.jpeg",
      "DRP-0244_p3_9.jpeg",
      "DRP-0244_p4_1.jpeg",
      "DRP-0244_p4_2.jpeg",
      "DRP-0244_p4_3.jpeg",
      "DRP-0244_p4_4.jpeg",
      "DRP-0244_p4_5.jpeg",
      "DRP-0244_p4_6.jpeg",
      "DRP-0244_p4_7.jpeg",
      "DRP-0244_p4_8.jpeg",
      "DRP-0244_p4_9.jpeg"
    ],
    "DRP-0245": [
      "DRP-0245_p3_1.jpeg",
      "DRP-0245_p3_2.jpeg",
      "DRP-0245_p3_3.jpeg",
      "DRP-0245_p3_4.jpeg",
      "DRP-0245_p3_5.jpeg",
      "DRP-0245_p3_6.jpeg",
      "DRP-0245_p3_7.jpeg",
      "DRP-0245_p3_8.jpeg",
      "DRP-0245_p3_9.jpeg",
      "DRP-0245_p4_1.jpeg",
      "DRP-0245_p4_2.jpeg",
      "DRP-0245_p4_3.jpeg",
      "DRP-0245_p4_4.jpeg"
    ],
    "DRP-0246": [
      "DRP-0246_p3_1.jpeg"
    ],
    "DRP-0247": [
      "DRP-0247_p3_1.jpeg",
      "DRP-0247_p3_2.jpeg",
      "DRP-0247_p3_3.jpeg",
      "DRP-0247_p3_4.jpeg",
      "DRP-0247_p3_5.jpeg",
      "DRP-0247_p3_6.jpeg",
      "DRP-0247_p3_7.jpeg",
      "DRP-0247_p3_8.jpeg",
      "DRP-0247_p3_9.jpeg",
      "DRP-0247_p4_1.jpeg",
      "DRP-0247_p4_2.jpeg",
      "DRP-0247_p4_3.jpeg",
      "DRP-0247_p4_4.jpeg",
      "DRP-0247_p4_5.jpeg",
      "DRP-0247_p4_6.jpeg",
      "DRP-0247_p4_7.jpeg",
      "DRP-0247_p4_8.jpeg",
      "DRP-0247_p4_9.jpeg"
    ],
    "DRP-0248": [
      "DRP-0248_p3_1.jpeg",
      "DRP-0248_p3_2.jpeg",
      "DRP-0248_p3_3.jpeg",
      "DRP-0248_p3_4.jpeg",
      "DRP-0248_p3_5.jpeg",
      "DRP-0248_p3_6.jpeg",
      "DRP-0248_p3_7.jpeg",
      "DRP-0248_p3_8.jpeg",
      "DRP-0248_p3_9.jpeg",
      "DRP-0248_p4_1.jpeg",
      "DRP-0248_p4_2.jpeg",
      "DRP-0248_p4_3.jpeg",
      "DRP-0248_p4_4.jpeg",
      "DRP-0248_p4_5.jpeg",
      "DRP-0248_p4_6.jpeg",
      "DRP-0248_p4_7.jpeg",
      "DRP-0248_p4_8.jpeg",
      "DRP-0248_p4_9.jpeg"
    ],
    "DRP-0249": [
      "DRP-0249_p3_1.jpeg",
      "DRP-0249_p3_2.jpeg",
      "DRP-0249_p3_3.jpeg",
      "DRP-0249_p3_4.jpeg",
      "DRP-0249_p3_5.jpeg",
      "DRP-0249_p3_6.jpeg",
      "DRP-0249_p3_7.jpeg",
      "DRP-0249_p3_8.jpeg",
      "DRP-0249_p3_9.jpeg",
      "DRP-0249_p4_1.jpeg",
      "DRP-0249_p4_2.jpeg",
      "DRP-0249_p4_3.jpeg",
      "DRP-0249_p4_4.jpeg",
      "DRP-0249_p4_5.jpeg",
      "DRP-0249_p4_6.jpeg",
      "DRP-0249_p4_7.jpeg",
      "DRP-0249_p4_8.jpeg",
      "DRP-0249_p4_9.jpeg"
    ],
    "DRP-0250": [
      "DRP-0250_p3_1.jpeg",
      "DRP-0250_p3_2.jpeg",
      "DRP-0250_p3_3.jpeg",
      "DRP-0250_p3_4.jpeg",
      "DRP-0250_p3_5.jpeg",
      "DRP-0250_p3_6.jpeg",
      "DRP-0250_p3_7.jpeg",
      "DRP-0250_p3_8.jpeg",
      "DRP-0250_p3_9.jpeg",
      "DRP-0250_p4_1.jpeg",
      "DRP-0250_p4_2.jpeg",
      "DRP-0250_p4_3.jpeg",
      "DRP-0250_p4_4.jpeg",
      "DRP-0250_p4_5.jpeg",
      "DRP-0250_p4_6.jpeg",
      "DRP-0250_p4_7.jpeg",
      "DRP-0250_p4_8.jpeg",
      "DRP-0250_p4_9.jpeg"
    ],
    "DRP-0251": [
      "DRP-0251_p3_1.jpeg",
      "DRP-0251_p3_2.jpeg",
      "DRP-0251_p3_3.jpeg",
      "DRP-0251_p3_4.jpeg",
      "DRP-0251_p3_5.jpeg",
      "DRP-0251_p3_6.jpeg",
      "DRP-0251_p3_7.jpeg",
      "DRP-0251_p3_8.jpeg",
      "DRP-0251_p3_9.jpeg",
      "DRP-0251_p4_1.jpeg",
      "DRP-0251_p4_2.jpeg",
      "DRP-0251_p4_3.jpeg",
      "DRP-0251_p4_4.jpeg",
      "DRP-0251_p4_5.jpeg",
      "DRP-0251_p4_6.jpeg",
      "DRP-0251_p4_7.jpeg",
      "DRP-0251_p4_8.jpeg",
      "DRP-0251_p4_9.jpeg"
    ],
    "DRP-0252": [
      "DRP-0252_p3_1.jpeg",
      "DRP-0252_p3_2.jpeg",
      "DRP-0252_p3_3.jpeg",
      "DRP-0252_p3_4.jpeg",
      "DRP-0252_p3_5.jpeg",
      "DRP-0252_p3_6.jpeg",
      "DRP-0252_p4_1.jpeg",
      "DRP-0252_p4_2.jpeg",
      "DRP-0252_p4_3.jpeg",
      "DRP-0252_p4_4.jpeg",
      "DRP-0252_p4_5.jpeg",
      "DRP-0252_p4_6.jpeg",
      "DRP-0252_p4_7.jpeg",
      "DRP-0252_p4_8.jpeg",
      "DRP-0252_p4_9.jpeg"
    ],
    "DRP-0253": [
      "DRP-0253_p3_1.jpeg"
    ],
    "DRP-0254": [
      "DRP-0254_p3_1.jpeg",
      "DRP-0254_p3_2.jpeg",
      "DRP-0254_p3_3.jpeg",
      "DRP-0254_p3_4.jpeg",
      "DRP-0254_p3_5.jpeg",
      "DRP-0254_p3_6.jpeg",
      "DRP-0254_p3_7.jpeg",
      "DRP-0254_p3_8.jpeg",
      "DRP-0254_p3_9.jpeg",
      "DRP-0254_p4_1.jpeg",
      "DRP-0254_p4_2.jpeg",
      "DRP-0254_p4_3.jpeg",
      "DRP-0254_p4_4.jpeg",
      "DRP-0254_p4_5.jpeg",
      "DRP-0254_p4_6.jpeg",
      "DRP-0254_p4_7.jpeg",
      "DRP-0254_p4_8.jpeg",
      "DRP-0254_p4_9.jpeg"
    ],
    "DRP-0255": [
      "DRP-0255_p3_1.jpeg",
      "DRP-0255_p3_2.jpeg",
      "DRP-0255_p3_3.jpeg",
      "DRP-0255_p3_4.jpeg",
      "DRP-0255_p3_5.jpeg",
      "DRP-0255_p3_6.jpeg",
      "DRP-0255_p4_1.jpeg",
      "DRP-0255_p4_2.jpeg",
      "DRP-0255_p4_3.jpeg",
      "DRP-0255_p4_4.jpeg",
      "DRP-0255_p4_5.jpeg",
      "DRP-0255_p4_6.jpeg",
      "DRP-0255_p4_7.jpeg",
      "DRP-0255_p4_8.jpeg",
      "DRP-0255_p4_9.jpeg"
    ],
    "DRP-0256": [
      "DRP-0256_p3_1.jpeg",
      "DRP-0256_p3_2.jpeg",
      "DRP-0256_p3_3.jpeg",
      "DRP-0256_p3_4.jpeg",
      "DRP-0256_p3_5.jpeg",
      "DRP-0256_p3_6.jpeg",
      "DRP-0256_p4_1.jpeg",
      "DRP-0256_p4_2.jpeg",
      "DRP-0256_p4_3.jpeg",
      "DRP-0256_p4_4.jpeg",
      "DRP-0256_p4_5.jpeg",
      "DRP-0256_p4_6.jpeg",
      "DRP-0256_p4_7.jpeg",
      "DRP-0256_p4_8.jpeg",
      "DRP-0256_p4_9.jpeg"
    ],
    "DRP-0257": [
      "DRP-0257_p3_1.jpeg",
      "DRP-0257_p3_2.jpeg",
      "DRP-0257_p3_3.jpeg",
      "DRP-0257_p3_4.jpeg",
      "DRP-0257_p3_5.jpeg",
      "DRP-0257_p3_6.jpeg",
      "DRP-0257_p3_7.jpeg",
      "DRP-0257_p3_8.jpeg",
      "DRP-0257_p3_9.jpeg",
      "DRP-0257_p4_1.jpeg",
      "DRP-0257_p4_2.jpeg",
      "DRP-0257_p4_3.jpeg",
      "DRP-0257_p4_4.jpeg",
      "DRP-0257_p4_5.jpeg",
      "DRP-0257_p4_6.jpeg",
      "DRP-0257_p4_7.jpeg",
      "DRP-0257_p4_8.jpeg",
      "DRP-0257_p4_9.jpeg"
    ],
    "DRP-0258": [
      "DRP-0258_p3_1.jpeg",
      "DRP-0258_p3_2.jpeg",
      "DRP-0258_p3_3.jpeg",
      "DRP-0258_p3_4.jpeg",
      "DRP-0258_p3_5.jpeg",
      "DRP-0258_p3_6.jpeg",
      "DRP-0258_p3_7.jpeg",
      "DRP-0258_p3_8.jpeg",
      "DRP-0258_p3_9.jpeg",
      "DRP-0258_p4_1.jpeg",
      "DRP-0258_p4_2.jpeg",
      "DRP-0258_p4_3.jpeg",
      "DRP-0258_p4_4.jpeg",
      "DRP-0258_p4_5.jpeg",
      "DRP-0258_p4_6.jpeg",
      "DRP-0258_p4_7.jpeg",
      "DRP-0258_p4_8.jpeg",
      "DRP-0258_p4_9.jpeg"
    ],
    "DRP-0259": [
      "DRP-0259_p3_1.jpeg",
      "DRP-0259_p3_2.jpeg",
      "DRP-0259_p3_3.jpeg",
      "DRP-0259_p3_4.jpeg",
      "DRP-0259_p3_5.jpeg",
      "DRP-0259_p3_6.jpeg",
      "DRP-0259_p3_7.jpeg",
      "DRP-0259_p3_8.jpeg",
      "DRP-0259_p3_9.jpeg",
      "DRP-0259_p4_1.jpeg",
      "DRP-0259_p4_2.jpeg",
      "DRP-0259_p4_3.jpeg",
      "DRP-0259_p4_4.jpeg",
      "DRP-0259_p4_5.jpeg",
      "DRP-0259_p4_6.jpeg",
      "DRP-0259_p4_7.jpeg",
      "DRP-0259_p4_8.jpeg",
      "DRP-0259_p4_9.jpeg"
    ],
    "DRP-0260": [
      "DRP-0260_p3_1.jpeg",
      "DRP-0260_p3_2.jpeg",
      "DRP-0260_p3_3.jpeg",
      "DRP-0260_p3_4.jpeg",
      "DRP-0260_p3_5.jpeg",
      "DRP-0260_p3_6.jpeg",
      "DRP-0260_p4_1.jpeg",
      "DRP-0260_p4_2.jpeg",
      "DRP-0260_p4_3.jpeg",
      "DRP-0260_p4_4.jpeg",
      "DRP-0260_p4_5.jpeg",
      "DRP-0260_p4_6.jpeg",
      "DRP-0260_p4_7.jpeg",
      "DRP-0260_p4_8.jpeg",
      "DRP-0260_p4_9.jpeg"
    ],
    "DRP-0261": [
      "DRP-0261_p3_1.jpeg",
      "DRP-0261_p3_2.jpeg",
      "DRP-0261_p3_3.jpeg",
      "DRP-0261_p3_4.jpeg",
      "DRP-0261_p3_5.jpeg",
      "DRP-0261_p3_6.jpeg",
      "DRP-0261_p4_1.jpeg",
      "DRP-0261_p4_2.jpeg",
      "DRP-0261_p4_3.jpeg",
      "DRP-0261_p4_4.jpeg",
      "DRP-0261_p4_5.jpeg",
      "DRP-0261_p4_6.jpeg",
      "DRP-0261_p4_7.jpeg",
      "DRP-0261_p4_8.jpeg",
      "DRP-0261_p4_9.jpeg"
    ],
    "DRP-0262": [
      "DRP-0262_p3_1.jpeg",
      "DRP-0262_p3_2.jpeg",
      "DRP-0262_p3_3.jpeg",
      "DRP-0262_p3_4.jpeg",
      "DRP-0262_p3_5.jpeg",
      "DRP-0262_p3_6.jpeg",
      "DRP-0262_p4_1.jpeg",
      "DRP-0262_p4_2.jpeg",
      "DRP-0262_p4_3.jpeg",
      "DRP-0262_p4_4.jpeg",
      "DRP-0262_p4_5.jpeg",
      "DRP-0262_p4_6.jpeg",
      "DRP-0262_p4_7.jpeg",
      "DRP-0262_p4_8.jpeg",
      "DRP-0262_p4_9.jpeg"
    ],
    "DRP-0263": [
      "DRP-0263_p3_1.jpeg",
      "DRP-0263_p3_2.jpeg",
      "DRP-0263_p3_3.jpeg",
      "DRP-0263_p3_4.jpeg",
      "DRP-0263_p3_5.jpeg",
      "DRP-0263_p3_6.jpeg",
      "DRP-0263_p4_1.jpeg",
      "DRP-0263_p4_2.jpeg",
      "DRP-0263_p4_3.jpeg",
      "DRP-0263_p4_4.jpeg",
      "DRP-0263_p4_5.jpeg",
      "DRP-0263_p4_6.jpeg",
      "DRP-0263_p4_7.jpeg",
      "DRP-0263_p4_8.jpeg",
      "DRP-0263_p4_9.jpeg"
    ],
    "DRP-0264": [
      "DRP-0264_p3_1.jpeg",
      "DRP-0264_p3_2.jpeg",
      "DRP-0264_p3_3.jpeg",
      "DRP-0264_p3_4.jpeg",
      "DRP-0264_p3_5.jpeg",
      "DRP-0264_p3_6.jpeg",
      "DRP-0264_p4_1.jpeg",
      "DRP-0264_p4_2.jpeg",
      "DRP-0264_p4_3.jpeg",
      "DRP-0264_p4_4.jpeg",
      "DRP-0264_p4_5.jpeg",
      "DRP-0264_p4_6.jpeg",
      "DRP-0264_p4_7.jpeg",
      "DRP-0264_p4_8.jpeg",
      "DRP-0264_p4_9.jpeg"
    ],
    "DRP-0265": [
      "DRP-0265_p3_1.jpeg",
      "DRP-0265_p3_2.jpeg",
      "DRP-0265_p3_3.jpeg",
      "DRP-0265_p3_4.jpeg",
      "DRP-0265_p4_1.jpeg",
      "DRP-0265_p4_2.jpeg",
      "DRP-0265_p4_3.jpeg",
      "DRP-0265_p4_4.jpeg",
      "DRP-0265_p4_5.jpeg",
      "DRP-0265_p4_6.jpeg"
    ],
    "DRP-0267": [
      "DRP-0267_p3_1.jpeg",
      "DRP-0267_p3_2.jpeg",
      "DRP-0267_p4_1.jpeg",
      "DRP-0267_p4_2.jpeg",
      "DRP-0267_p4_3.jpeg",
      "DRP-0267_p4_4.jpeg",
      "DRP-0267_p4_5.jpeg",
      "DRP-0267_p4_6.jpeg",
      "DRP-0267_p4_7.jpeg",
      "DRP-0267_p4_8.jpeg",
      "DRP-0267_p4_9.jpeg"
    ],
    "DRP-0268": [
      "DRP-0268_p3_1.jpeg",
      "DRP-0268_p3_2.jpeg",
      "DRP-0268_p3_3.jpeg",
      "DRP-0268_p3_4.jpeg",
      "DRP-0268_p4_1.jpeg",
      "DRP-0268_p4_2.jpeg",
      "DRP-0268_p4_3.jpeg",
      "DRP-0268_p4_4.jpeg",
      "DRP-0268_p4_5.jpeg",
      "DRP-0268_p4_6.jpeg",
      "DRP-0268_p4_7.jpeg",
      "DRP-0268_p4_8.jpeg",
      "DRP-0268_p4_9.jpeg"
    ],
    "DRP-0269": [
      "DRP-0269_p3_1.jpeg",
      "DRP-0269_p3_2.jpeg",
      "DRP-0269_p3_3.jpeg",
      "DRP-0269_p3_4.jpeg",
      "DRP-0269_p4_1.jpeg",
      "DRP-0269_p4_2.jpeg",
      "DRP-0269_p4_3.jpeg",
      "DRP-0269_p4_4.jpeg",
      "DRP-0269_p4_5.jpeg",
      "DRP-0269_p4_6.jpeg",
      "DRP-0269_p4_7.jpeg",
      "DRP-0269_p4_8.jpeg",
      "DRP-0269_p4_9.jpeg"
    ],
    "DRP-0270": [
      "DRP-0270_p3_1.jpeg",
      "DRP-0270_p3_2.jpeg",
      "DRP-0270_p3_3.jpeg",
      "DRP-0270_p3_4.jpeg",
      "DRP-0270_p4_1.jpeg",
      "DRP-0270_p4_2.jpeg",
      "DRP-0270_p4_3.jpeg",
      "DRP-0270_p4_4.jpeg",
      "DRP-0270_p4_5.jpeg",
      "DRP-0270_p4_6.jpeg",
      "DRP-0270_p4_7.jpeg",
      "DRP-0270_p4_8.jpeg",
      "DRP-0270_p4_9.jpeg"
    ],
    "DRP-0271": [
      "DRP-0271_p3_1.jpeg",
      "DRP-0271_p3_2.jpeg",
      "DRP-0271_p4_1.jpeg",
      "DRP-0271_p4_2.jpeg",
      "DRP-0271_p4_3.jpeg",
      "DRP-0271_p4_4.jpeg",
      "DRP-0271_p4_5.jpeg",
      "DRP-0271_p4_6.jpeg",
      "DRP-0271_p4_7.jpeg",
      "DRP-0271_p4_8.jpeg",
      "DRP-0271_p4_9.jpeg"
    ],
    "DRP-0272": [
      "DRP-0272_p3_1.jpeg",
      "DRP-0272_p3_2.jpeg",
      "DRP-0272_p4_1.jpeg",
      "DRP-0272_p4_2.jpeg",
      "DRP-0272_p4_3.jpeg",
      "DRP-0272_p4_4.jpeg",
      "DRP-0272_p4_5.jpeg",
      "DRP-0272_p4_6.jpeg"
    ],
    "DRP-0273": [
      "DRP-0273_p3_1.jpeg",
      "DRP-0273_p3_2.jpeg",
      "DRP-0273_p4_1.jpeg",
      "DRP-0273_p4_2.jpeg",
      "DRP-0273_p4_3.jpeg",
      "DRP-0273_p4_4.jpeg",
      "DRP-0273_p4_5.jpeg",
      "DRP-0273_p4_6.jpeg",
      "DRP-0273_p4_7.jpeg",
      "DRP-0273_p4_8.jpeg",
      "DRP-0273_p4_9.jpeg"
    ],
    "DRP-0274": [
      "DRP-0274_p3_1.jpeg",
      "DRP-0274_p3_2.jpeg",
      "DRP-0274_p4_1.jpeg",
      "DRP-0274_p4_2.jpeg",
      "DRP-0274_p4_3.jpeg",
      "DRP-0274_p4_4.jpeg",
      "DRP-0274_p4_5.jpeg",
      "DRP-0274_p4_6.jpeg",
      "DRP-0274_p4_7.jpeg",
      "DRP-0274_p4_8.jpeg",
      "DRP-0274_p4_9.jpeg"
    ],
    "DRP-0275": [
      "DRP-0275_p3_1.jpeg",
      "DRP-0275_p3_2.jpeg",
      "DRP-0275_p4_1.jpeg",
      "DRP-0275_p4_2.jpeg",
      "DRP-0275_p4_3.jpeg",
      "DRP-0275_p4_4.jpeg",
      "DRP-0275_p4_5.jpeg",
      "DRP-0275_p4_6.jpeg",
      "DRP-0275_p4_7.jpeg",
      "DRP-0275_p4_8.jpeg",
      "DRP-0275_p4_9.jpeg"
    ],
    "DRP-0276": [
      "DRP-0276_p3_1.jpeg",
      "DRP-0276_p3_2.jpeg",
      "DRP-0276_p4_1.jpeg",
      "DRP-0276_p4_2.jpeg",
      "DRP-0276_p4_3.jpeg",
      "DRP-0276_p4_4.jpeg",
      "DRP-0276_p4_5.jpeg",
      "DRP-0276_p4_6.jpeg",
      "DRP-0276_p4_7.jpeg",
      "DRP-0276_p4_8.jpeg",
      "DRP-0276_p4_9.jpeg"
    ],
    "DRP-0277": [
      "DRP-0277_p3_1.jpeg",
      "DRP-0277_p3_2.jpeg",
      "DRP-0277_p4_1.jpeg",
      "DRP-0277_p4_2.jpeg",
      "DRP-0277_p4_3.jpeg",
      "DRP-0277_p4_4.jpeg",
      "DRP-0277_p4_5.jpeg",
      "DRP-0277_p4_6.jpeg",
      "DRP-0277_p4_7.jpeg",
      "DRP-0277_p4_8.jpeg",
      "DRP-0277_p4_9.jpeg"
    ]
  }
}